pynanolab/__init__.py
pynanolab/__main__.py
pynanolab/_version.cp313-win_amd64.pyd
pynanolab/pynanolabgui.cp313-win_amd64.pyd
pynanolab/start.py
pynanolab/apps/__init__.py
pynanolab/apps/clustering/__init__.py
pynanolab/apps/clustering/clusterform.cp313-win_amd64.pyd
pynanolab/apps/clustering/pnlcluster.cp313-win_amd64.pyd
pynanolab/apps/clustering/pnlclusterentrance.cp313-win_amd64.pyd
pynanolab/apps/clustering/pnlclusterwidget.cp313-win_amd64.pyd
pynanolab/apps/curveFitting/__init__.py
pynanolab/apps/curveFitting/curvefitentrance.cp313-win_amd64.pyd
pynanolab/apps/curveFitting/curvefitform.cp313-win_amd64.pyd
pynanolab/apps/curveFitting/curvefitwidget.cp313-win_amd64.pyd
pynanolab/apps/curveFitting/lmfparmsmodel.cp313-win_amd64.pyd
pynanolab/apps/curveFitting/lmfparmtable.cp313-win_amd64.pyd
pynanolab/apps/curveFitting/funcmodel/__init__.py
pynanolab/apps/curveFitting/funcmodel/basefunction.cp313-win_amd64.pyd
pynanolab/apps/curveFitting/funcmodel/pnlfitmodel.cp313-win_amd64.pyd
pynanolab/apps/preprocessing/__init__.py
pynanolab/apps/preprocessing/baseline.cp313-win_amd64.pyd
pynanolab/apps/preprocessing/denoise.cp313-win_amd64.pyd
pynanolab/apps/preprocessing/loess.cp313-win_amd64.pyd
pynanolab/apps/preprocessing/normalization.cp313-win_amd64.pyd
pynanolab/apps/signalExtraction/__init__.py
pynanolab/apps/signalExtraction/adept.cp313-win_amd64.pyd
pynanolab/apps/signalExtraction/adept2state.cp313-win_amd64.pyd
pynanolab/apps/signalExtraction/stepResponse.cp313-win_amd64.pyd
pynanolab/apps/signalfrequency/__init__.py
pynanolab/apps/signalfrequency/filter.cp313-win_amd64.pyd
pynanolab/apps/signalfrequency/pnlfft.cp313-win_amd64.pyd
pynanolab/apps/signalfrequency/shortfft.cp313-win_amd64.pyd
pynanolab/apps/signalfrequency/superlets.cp313-win_amd64.pyd
pynanolab/apps/signalfrequency/ephys_nlm/__init__.py
pynanolab/apps/signalfrequency/ephys_nlm/_outputrecordingextractor.cp313-win_amd64.pyd
pynanolab/apps/signalfrequency/ephys_nlm/ephys_nlm.cp313-win_amd64.pyd
pynanolab-3.1.0.dist-info/licenses/license.txt
pynanolab-3.1.0.dist-info/METADATA
pynanolab-3.1.0.dist-info/WHEEL
pynanolab-3.1.0.dist-info/entry_points.txt
pynanolab-3.1.0.dist-info/top_level.txt
pynanolab-3.1.0.dist-info/RECORD
