Metadata-Version: 2.4
Name: pynanolab
Version: 3.1.0
Summary: A data analysis and visualization software
Home-page: https://github.com/decacent/PyNanoLab
Author: Shaochuang Liu
Author-email: shaochuangliu@gmail.com
License: MIT
Classifier: Development Status :: 4 - Beta
Classifier: License :: OSI Approved :: MIT License
Classifier: Operating System :: Microsoft :: Windows
Classifier: Operating System :: POSIX :: Linux
Classifier: Operating System :: MacOS
Classifier: Programming Language :: Python :: 3.11
Classifier: Framework :: Matplotlib
Classifier: Topic :: Scientific/Engineering :: Visualization
Requires-Python: >=3.11
License-File: license.txt
Requires-Dist: numpy
Requires-Dist: PySide6<=6.8.3,>=6.6.1
Requires-Dist: matplotlib
Requires-Dist: scipy
Requires-Dist: npTDMS
Requires-Dist: sympy
Requires-Dist: requests
Requires-Dist: PyWaveLets
Requires-Dist: lmfit
Requires-Dist: pandas
Requires-Dist: seaborn
Requires-Dist: openpyxl
Requires-Dist: pyqtgraph
Requires-Dist: numexpr
Requires-Dist: pyinstaller
Requires-Dist: spectate
Requires-Dist: traitlets
Requires-Dist: psutil
Requires-Dist: tftb
Requires-Dist: chardet
Requires-Dist: tabulate
Requires-Dist: scikit-learn
Requires-Dist: tables
Requires-Dist: statsmodels
Requires-Dist: pybaselines
Requires-Dist: hdbscan
Requires-Dist: untangle
Requires-Dist: configobj
Requires-Dist: deepdiff
Requires-Dist: qtconsole
Requires-Dist: pyshortcuts
Requires-Dist: spikeextractors
Requires-Dist: pyts
Requires-Dist: markdown
Requires-Dist: openai
Requires-Dist: pygments
Requires-Dist: ollama
Dynamic: author
Dynamic: author-email
Dynamic: classifier
Dynamic: description
Dynamic: description-content-type
Dynamic: home-page
Dynamic: license
Dynamic: license-file
Dynamic: requires-dist
Dynamic: requires-python
Dynamic: summary
